alerts/__init__.py
api/__init__.py
aws-s3/__init__.py
awss3/__init__.py
errors/__init__.py
hello_world/__init__.py
hello_world/main.py
logger/__init__.py
redshift/__init__.py
src/__init__.py
src/main.py
utils/__init__.py
utils/logger.py
utils/singleton.py
common_integration_yom-0.2.7.dist-info/LICENSE.txt
common_integration_yom-0.2.7.dist-info/METADATA
common_integration_yom-0.2.7.dist-info/WHEEL
common_integration_yom-0.2.7.dist-info/top_level.txt
common_integration_yom-0.2.7.dist-info/RECORD
