Metadata-Version: 2.1
Name: common-integration-yom
Version: 0.2.7
Summary: A common integration package
Home-page: https://github.com/kaizen-group/yom-integration-package
Author: Yom
Author-email: data@youorder.me
License: UNKNOWN
Platform: UNKNOWN
Classifier: Programming Language :: Python :: 3.8
Classifier: License :: OSI Approved :: MIT License
Classifier: Operating System :: OS Independent
Requires-Python: >=3.6
Requires-Dist: requests (==2.25.0)
Requires-Dist: bunyan (==0.1.2)
Requires-Dist: pandas (==1.0.5)
Requires-Dist: sqlalchemy (==1.3.18)
